{
	"configurations" : 
	[
		{
			"directories" : 
			[
				{
					"build" : ".",
					"childIndexes" : 
					[
						1
					],
					"jsonFile" : "directory-.-Debug-f5ebdc15457944623624.json",
					"minimumCMakeVersion" : 
					{
						"string" : "3.10"
					},
					"projectIndex" : 0,
					"source" : ".",
					"targetIndexes" : 
					[
						0,
						1
					]
				},
				{
					"build" : "mylib_dir_TD1",
					"jsonFile" : "directory-mylib_dir_TD1-Debug-c0d34f020f736e0635bc.json",
					"minimumCMakeVersion" : 
					{
						"string" : "3.10"
					},
					"parentIndex" : 0,
					"projectIndex" : 0,
					"source" : "mylib_dir_TD1",
					"targetIndexes" : 
					[
						2
					]
				}
			],
			"name" : "Debug",
			"projects" : 
			[
				{
					"directoryIndexes" : 
					[
						0,
						1
					],
					"name" : "Tutorial",
					"targetIndexes" : 
					[
						0,
						1,
						2
					]
				}
			],
			"targets" : 
			[
				{
					"directoryIndex" : 0,
					"id" : "Main.exe::@6890427a1f51a3e7e1df",
					"jsonFile" : "target-Main.exe-Debug-ee4f655b9c77e4c2f6c8.json",
					"name" : "Main.exe",
					"projectIndex" : 0
				},
				{
					"directoryIndex" : 0,
					"id" : "Test.exe::@6890427a1f51a3e7e1df",
					"jsonFile" : "target-Test.exe-Debug-25d145dd25f5435b1907.json",
					"name" : "Test.exe",
					"projectIndex" : 0
				},
				{
					"directoryIndex" : 1,
					"id" : "mylib::@ca42239461999a6bad77",
					"jsonFile" : "target-mylib-Debug-e4a9309859833a4b28fd.json",
					"name" : "mylib",
					"projectIndex" : 0
				}
			]
		}
	],
	"kind" : "codemodel",
	"paths" : 
	{
		"build" : "/home/yyz/\u6587\u6863/chps2023/TDs/build",
		"source" : "/home/yyz/\u6587\u6863/chps2023/TDs"
	},
	"version" : 
	{
		"major" : 2,
		"minor" : 3
	}
}
